primer_explorer/__init__.py
primer_explorer/_version.py
primer_explorer/combinations.py
primer_explorer/config.py
primer_explorer/dust_score.py
primer_explorer/gff.py
primer_explorer/kmer.py
primer_explorer/pcr.py
primer_explorer/plot.py
primer_explorer/regions.py
primer_explorer/report.py
primer_explorer/seq_filters.py
primer_explorer/stats.py
primer_explorer/utils.py
primer_explorer/version_manager.py
primer_explorer/primer3/__init__.py
primer_explorer/primer3/primer3.py
primer_explorer/primer3/bin/primer3_core
primer_explorer/primer3/primer3_config/dangle.dh
primer_explorer/primer3/primer3_config/dangle.ds
primer_explorer/primer3/primer3_config/loops.dh
primer_explorer/primer3/primer3_config/loops.ds
primer_explorer/primer3/primer3_config/stack.dh
primer_explorer/primer3/primer3_config/stack.ds
primer_explorer/primer3/primer3_config/stackmm.dh
primer_explorer/primer3/primer3_config/stackmm.ds
primer_explorer/primer3/primer3_config/tetraloop.dh
primer_explorer/primer3/primer3_config/tetraloop.ds
primer_explorer/primer3/primer3_config/triloop.dh
primer_explorer/primer3/primer3_config/triloop.ds
primer_explorer/primer3/primer3_config/tstack.dh
primer_explorer/primer3/primer3_config/tstack2.dh
primer_explorer/primer3/primer3_config/tstack2.ds
primer_explorer/primer3/primer3_config/tstack_tm_inf.ds
primer_explorer/primer3/primer3_config/interpretations/dangle_i.dh
primer_explorer/primer3/primer3_config/interpretations/dangle_i.ds
primer_explorer/primer3/primer3_config/interpretations/loops_i.dh
primer_explorer/primer3/primer3_config/interpretations/loops_i.ds
primer_explorer/primer3/primer3_config/interpretations/stack_i.dh
primer_explorer/primer3/primer3_config/interpretations/stack_i.ds
primer_explorer/primer3/primer3_config/interpretations/stackmm_i_mm.dh
primer_explorer/primer3/primer3_config/interpretations/stackmm_i_mm.ds
primer_explorer/primer3/primer3_config/interpretations/tetraloop_i.dh
primer_explorer/primer3/primer3_config/interpretations/tetraloop_i.ds
primer_explorer2-0.5.6.dist-info/LICENSE.txt
primer_explorer2-0.5.6.dist-info/METADATA
primer_explorer2-0.5.6.dist-info/WHEEL
primer_explorer2-0.5.6.dist-info/top_level.txt
primer_explorer2-0.5.6.dist-info/RECORD
