Metadata-Version: 2.1
Name: primer-explorer2
Version: 0.5.6
Summary: A small library to help K-seq users to select primers.
Home-page: https://github.com/pziarsolo/primer_explorer2
Author: P.Ziarsolo
Author-email: pziarsolo@gmail.com
License: GNU General Public License v3.0
Platform: UNKNOWN
Classifier: Programming Language :: Python :: 3
Classifier: License :: OSI Approved :: MIT License
Classifier: Operating System :: OS Independent
Requires-Python: >=3.6
License-File: LICENSE.txt
Requires-Dist: matplotlib
Requires-Dist: openpyxl
Requires-Dist: pyranges
Requires-Dist: pandas
